README.md
setup.py
alab_experiment_helper/__init__.py
alab_experiment_helper/experiment.py
alab_experiment_helper/sample.py
alab_experiment_helper.egg-info/PKG-INFO
alab_experiment_helper.egg-info/SOURCES.txt
alab_experiment_helper.egg-info/dependency_links.txt
alab_experiment_helper.egg-info/not-zip-safe
alab_experiment_helper.egg-info/requires.txt
alab_experiment_helper.egg-info/top_level.txt
alab_experiment_helper/tasks/__init__.py
alab_experiment_helper/tasks/base.py
alab_experiment_helper/tasks/dispensing.py
alab_experiment_helper/tasks/disposing.py
alab_experiment_helper/tasks/heating.py
alab_experiment_helper/tasks/heating_with_atmosphere.py
alab_experiment_helper/tasks/scraping.py
alab_experiment_helper/tasks/xrd.py